{"uuid": "8d5a42ea-91dd-4cc3-b748-6d9693eb0676", "filetype": 15, "filetype_sub": 1, "namespace": ["character", "student", "hanako_swimsuit", "bond", "02"], "name": {"en": "No Witnesses, No Point", "jp": "No Witnesses, No Point", "zh_cn": "没人看就没有意义"}, "desc": [{"en": "Sensei is enjoying nature by a waterfall when the sound of Hanako's singing shatters the peace. Frustrated that Sensei is keeping their distance, Hanako splashes water at them.", "jp": "Sensei is enjoying nature by a waterfall when the sound of Hanako's singing shatters the peace. Frustrated that Sensei is keeping their distance, Hanako splashes water at them.", "zh_cn": "散步时，老师听见了{cf花子}的歌声。{cf花子}正在瀑布前的湖中感受着大自然。眼见老师拒绝入水，对自己保持距离，{cf花子}动起了歪脑筋，将老师一把拉入水中。"}], "pos": {"student": "HANAKO_SWIMSUIT", "no": 2, "favor_rank": 3}, "image": {"platform": -1, "value": "", "short_desc": ""}, "instance_id": "BOND_HANAKO_SWIMSUIT_2_3", "part": {"all": {"background": {"BG_ForestRoad.jpg": {"uuid": "b54d7808-af11-4bf2-91db-5d2dcc664637", "filetype": 71, "filename": "BG_ForestRoad.jpg", "name": {"en": "BG_ForestRoad.jpg", "jp": "BG_ForestRoad.jpg", "zh_cn": "BG_ForestRoad.jpg"}, "desc": {"en": "BG_ForestRoad.jpg Description", "jp": "BG_ForestRoad.jpg Description", "zh_cn": "BG_ForestRoad.jpg Description"}, "image": {"platform": {"en": "None", "jp": "None", "zh_cn": "None"}, "value": "/static/images/background/BG_ForestRoad.jpg", "short_desc": {"en": "", "jp": "", "zh_cn": ""}}, "character": [], "interpage": {"prev": {"name": {"en": "BG_ForestRailRoad_Fog.jpg", "jp": "BG_ForestRailRoad_Fog.jpg", "zh_cn": "BG_ForestRailRoad_Fog.jpg"}, "namespace": ["background", "BG_ForestRailRoad_Fog.jpg"]}, "next": {"name": {"en": "BG_ForestRoad_Night.jpg", "jp": "BG_ForestRoad_Night.jpg", "zh_cn": "BG_ForestRoad_Night.jpg"}, "namespace": ["background", "BG_ForestRoad_Night.jpg"]}}}, "BG_WaterFall.jpg": {"uuid": "6bb2413f-8d3e-442c-95e1-906d99592f35", "filetype": 71, "filename": "BG_WaterFall.jpg", "name": {"en": "BG_WaterFall.jpg", "jp": "BG_WaterFall.jpg", "zh_cn": "BG_WaterFall.jpg"}, "desc": {"en": "BG_WaterFall.jpg Description", "jp": "BG_WaterFall.jpg Description", "zh_cn": "BG_WaterFall.jpg Description"}, "image": {"platform": {"en": "None", "jp": "None", "zh_cn": "None"}, "value": "/static/images/background/BG_WaterFall.jpg", "short_desc": {"en": "", "jp": "", "zh_cn": ""}}, "character": [], "interpage": {"prev": {"name": {"en": "BG_Ward_Night.jpg", "jp": "BG_Ward_Night.jpg", "zh_cn": "BG_Ward_Night.jpg"}, "namespace": ["background", "BG_Ward_Night.jpg"]}, "next": {"name": {"en": "BG_WaterFall_Night.jpg", "jp": "BG_WaterFall_Night.jpg", "zh_cn": "BG_WaterFall_Night.jpg"}, "namespace": ["background", "BG_WaterFall_Night.jpg"]}}}}, "character": {"Hanako_Swimsuit": {"uuid": "Hanako_Swimsuit", "id": 10074, "name": {"path_name": "Hanako_Swimsuit", "dev_name": "CH0209", "family_name": {"en": "Urawa", "jp": "浦和", "zh_cn_jp": "浦和", "zh_cn_tw": "浦和", "zh_cn_cn": "浦和"}, "personal_name": {"en": "Hanako", "jp": "ハナコ", "zh_cn_jp": "花子", "zh_cn_tw": "花子", "zh_cn_cn": "花子"}, "name": {"en": "Hanako (Swimsuit)", "jp": "ハナコ（水着）", "zh_cn_jp": "花子（泳装）", "zh_cn_tw": "花子(泳装)", "zh_cn_cn": "花子（泳装）"}}, "image": {"collection_bg": "BG_WaterFall", "collection_texture": "10074"}, "birthday": {"localized": {"en": "January 3rd", "jp": "1月3日", "zh_cn_jp": "1月3日", "zh_cn_tw": "1月3日", "zh_cn_cn": "1月3日"}, "normalized": {"en": "1/3", "jp": "1/3", "zh_cn_jp": "1/3", "zh_cn_tw": "1/3", "zh_cn_cn": "1/3"}}, "school": {"short": {"en": "Trinity", "jp": "トリニティ", "zh_cn_jp": "三一", "zh_cn_tw": "三一", "zh_cn_cn": "崔尼蒂"}, "long": {"en": "Trinity General School", "jp": "トリニティ総合学園", "zh_cn_jp": "三一综合学园", "zh_cn_tw": "三一综合学园", "zh_cn_cn": "崔尼蒂综合学院"}}, "school_id": "Trinity", "club": {"en": "Make-Up Work Club", "jp": "補習授業部", "zh_cn_jp": "补课部", "zh_cn_tw": "补课部", "zh_cn_cn": "补习部"}, "age": {"en": "16 years old", "jp": "16歳", "zh_cn_jp": "16岁", "zh_cn_tw": "16岁", "zh_cn_cn": "16岁"}, "hobby": {"en": "Taking walks", "jp": "徘徊", "zh_cn_jp": "徘徊", "zh_cn_tw": "散步", "zh_cn_cn": "徘徊"}, "interpage": {"prev": {"name": {"path_name": "Hanako", "dev_name": "Hanako", "name": {"en": "Hanako", "jp": "ハナコ", "zh_cn_jp": "花子", "zh_cn_tw": "花子", "zh_cn_cn": "花子"}}, "namespace": ["character", "student", "hanako"]}, "next": {"name": {"path_name": "Hare", "dev_name": "Hare", "name": {"en": "Hare", "jp": "ハレ", "zh_cn_jp": "晴", "zh_cn_tw": "晴", "zh_cn_cn": "晴"}}, "namespace": ["character", "student", "hare"]}}, "combatant_info": {"squad_type": {"type": "Main", "lang": {"en": "STRIKER", "jp": "STRIKER", "zh_cn_jp": "前锋", "zh_cn_tw": "STRIKER", "zh_cn_cn": "突击"}}, "attack_type": {"type": "Sonic", "lang": {"en": "Sonic", "jp": "振動", "zh_cn_jp": "振动", "zh_cn_tw": "振动", "zh_cn_cn": "振动"}}, "armor_type": {"type": "HeavyArmor", "lang": {"en": "Heavy", "jp": "重装甲", "zh_cn_jp": "重型装甲", "zh_cn_tw": "重装甲", "zh_cn_cn": "重装甲"}}}, "bond_track": {"uuid": "b6cd18b0-eae5-4f86-8bca-b943f184f9d5", "no": 9, "filetype": 1, "namespace": ["track", "ost", "9"], "track_type": 0, "instance_id": "OST_9", "name": {"realname": {"en": "Midsummer Cat", "jp": "Midsummer Cat", "zh_cn": "仲夏一猫"}, "known_as": []}, "desc": {"en": "【暂无】", "jp": "【暂无】", "zh_cn": "【暂无】"}, "composer": {"composer_id": "1", "nickname": "Mitsukiyo", "contact": {"platform": {"en": "Twitter", "jp": "Twitter", "zh_cn": "Twitter"}, "url": {"platform": {"en": "Twitter", "jp": "Twitter", "zh_cn": "Twitter"}, "value": "https://twitter.com/mitsukiyo_5", "short_desc": {"en": "", "jp": "", "zh_cn": ""}}}}, "tags": [{"uuid": "9ade045f-f24e-4f88-8af6-0458db3332ae", "filetype": 61, "name": {"en": "Relaxing", "jp": "Relaxing", "zh_cn": "轻松惬意"}, "desc": {"en": "Sometimes it's good to have a cup of tea and relaxed. <b>Example: Cherry Merry Berry</b>", "jp": "Sometimes it's good to have a cup of tea and relaxed. <b>Example: Cherry Merry Berry</b>", "zh_cn": "有些时候，停下来饮杯茶也不错。<b>举例/联想：Cherry Merry Berry</b>"}, "namespace": ["tag", "relaxing"], "color": "green", "color_css": "success", "interpage": {"prev": {"name": {"en": "Possibilities", "jp": "Possibilities", "zh_cn": "可能性"}, "namespace": ["tag", "possibilities"]}, "next": {"name": {"en": "Sad", "jp": "Sad", "zh_cn": "悲伤的"}, "namespace": ["tag", "sad"]}}}, {"uuid": "740e5356-bb52-4b4f-ab41-c62f6f5a6c09", "filetype": 61, "name": {"en": "Day to Day", "jp": "Day to Day", "zh_cn": "日常的"}, "desc": {"en": "Aside from all the ups and downs, we need some to to relax our mind. <b>Example: Lemonade Diary, Nesno wons.</b> Main characteristics are soft, gentle.", "jp": "Aside from all the ups and downs, we need some to to relax our mind. <b>Example: Lemonade Diary, Nesno wons.</b> Main characteristics are soft, gentle.", "zh_cn": "在大起大落的事情里外，我们总需要一点闲适的时间来放松自己的神经。<b>举例/联想：Lemonade Diary、Nesno wons；特征是较为温柔。</b>"}, "namespace": ["tag", "daytoday"], "color": "green", "color_css": "success", "interpage": {"prev": {"name": {"en": "Cheerful", "jp": "Cheerful", "zh_cn": "欢快"}, "namespace": ["tag", "cheerful"]}, "next": {"name": {"en": "Discouraged", "jp": "Discouraged", "zh_cn": "灰心的"}, "namespace": ["tag", "discouraged"]}}}], "image": {"platform": {"en": "None", "jp": "None", "zh_cn": "None"}, "value": "/static/images/background/BG_View_Kivotos.jpg", "short_desc": {"en": "", "jp": "", "zh_cn": ""}}, "album": [{"uuid": "80097a34-1ab3-4064-929a-ad18a2eecc36", "filetype": 5, "album_id": "01", "name": {"en": "Blue Archive Original Soundtrack (Vol.1 ~Longing for the memorable days~)", "jp": "Blue Archive Original Soundtrack (Vol.1 ~Longing for the memorable days~)", "zh_cn": "Blue Archive Original Soundtrack (Vol.1 ~Longing for the memorable days~)"}, "desc": {"en": "Blue Archive's first original soundtrack.", "jp": "Blue Archive's first original soundtrack.", "zh_cn": "Blue Archive's first original soundtrack."}, "namespace": ["album", "01"], "cover_img": "/static/images/album/01.png", "release_date": 1648080000, "release_date_format": "2022-03-24", "disc_num": 2, "track_num": 38}], "interpage": {"prev": {"name": {"realname": {"en": "Shady Girls", "jp": "Shady Girls", "zh_cn": "鬼鬼祟祟的女孩"}, "known_as": []}, "namespace": ["track", "ost", "8"], "instance_id": "OST_8", "no": 8}, "next": {"name": {"realname": {"en": "Romantic Smile", "jp": "Romantic Smile", "zh_cn": "浪漫一笑"}, "known_as": []}, "namespace": ["track", "ost", "10"], "instance_id": "OST_10", "no": 10}}, "stats": {"is_ost": true, "is_ani": false, "is_short": false, "is_other": false, "is_ba": true, "is_jp": true, "is_global": true, "is_cn": true, "is_story": true, "is_story_main": true, "is_story_memory": true, "is_story_event": true, "is_battle": false, "is_battle_main": false, "is_battle_story": false, "is_battle_event": false, "is_segment": false, "is_sub": false, "has_related": false}}, "bond_rank": 3}}, "track": {"OST_9": {"uuid": "b6cd18b0-eae5-4f86-8bca-b943f184f9d5", "no": 9, "filetype": 1, "namespace": ["track", "ost", "9"], "track_type": 0, "instance_id": "OST_9", "name": {"realname": {"en": "Midsummer Cat", "jp": "Midsummer Cat", "zh_cn": "仲夏一猫"}, "known_as": []}, "desc": {"en": "【暂无】", "jp": "【暂无】", "zh_cn": "【暂无】"}, "composer": {"composer_id": "1", "nickname": "Mitsukiyo", "contact": {"platform": {"en": "Twitter", "jp": "Twitter", "zh_cn": "Twitter"}, "url": {"platform": {"en": "Twitter", "jp": "Twitter", "zh_cn": "Twitter"}, "value": "https://twitter.com/mitsukiyo_5", "short_desc": {"en": "", "jp": "", "zh_cn": ""}}}}, "tags": [{"uuid": "9ade045f-f24e-4f88-8af6-0458db3332ae", "filetype": 61, "name": {"en": "Relaxing", "jp": "Relaxing", "zh_cn": "轻松惬意"}, "desc": {"en": "Sometimes it's good to have a cup of tea and relaxed. <b>Example: Cherry Merry Berry</b>", "jp": "Sometimes it's good to have a cup of tea and relaxed. <b>Example: Cherry Merry Berry</b>", "zh_cn": "有些时候，停下来饮杯茶也不错。<b>举例/联想：Cherry Merry Berry</b>"}, "namespace": ["tag", "relaxing"], "color": "green", "color_css": "success", "interpage": {"prev": {"name": {"en": "Possibilities", "jp": "Possibilities", "zh_cn": "可能性"}, "namespace": ["tag", "possibilities"]}, "next": {"name": {"en": "Sad", "jp": "Sad", "zh_cn": "悲伤的"}, "namespace": ["tag", "sad"]}}}, {"uuid": "740e5356-bb52-4b4f-ab41-c62f6f5a6c09", "filetype": 61, "name": {"en": "Day to Day", "jp": "Day to Day", "zh_cn": "日常的"}, "desc": {"en": "Aside from all the ups and downs, we need some to to relax our mind. <b>Example: Lemonade Diary, Nesno wons.</b> Main characteristics are soft, gentle.", "jp": "Aside from all the ups and downs, we need some to to relax our mind. <b>Example: Lemonade Diary, Nesno wons.</b> Main characteristics are soft, gentle.", "zh_cn": "在大起大落的事情里外，我们总需要一点闲适的时间来放松自己的神经。<b>举例/联想：Lemonade Diary、Nesno wons；特征是较为温柔。</b>"}, "namespace": ["tag", "daytoday"], "color": "green", "color_css": "success", "interpage": {"prev": {"name": {"en": "Cheerful", "jp": "Cheerful", "zh_cn": "欢快"}, "namespace": ["tag", "cheerful"]}, "next": {"name": {"en": "Discouraged", "jp": "Discouraged", "zh_cn": "灰心的"}, "namespace": ["tag", "discouraged"]}}}], "image": {"platform": {"en": "None", "jp": "None", "zh_cn": "None"}, "value": "/static/images/background/BG_View_Kivotos.jpg", "short_desc": {"en": "", "jp": "", "zh_cn": ""}}, "album": [{"uuid": "80097a34-1ab3-4064-929a-ad18a2eecc36", "filetype": 5, "album_id": "01", "name": {"en": "Blue Archive Original Soundtrack (Vol.1 ~Longing for the memorable days~)", "jp": "Blue Archive Original Soundtrack (Vol.1 ~Longing for the memorable days~)", "zh_cn": "Blue Archive Original Soundtrack (Vol.1 ~Longing for the memorable days~)"}, "desc": {"en": "Blue Archive's first original soundtrack.", "jp": "Blue Archive's first original soundtrack.", "zh_cn": "Blue Archive's first original soundtrack."}, "namespace": ["album", "01"], "cover_img": "/static/images/album/01.png", "release_date": 1648080000, "release_date_format": "2022-03-24", "disc_num": 2, "track_num": 38}], "interpage": {"prev": {"name": {"realname": {"en": "Shady Girls", "jp": "Shady Girls", "zh_cn": "鬼鬼祟祟的女孩"}, "known_as": []}, "namespace": ["track", "ost", "8"], "instance_id": "OST_8", "no": 8}, "next": {"name": {"realname": {"en": "Romantic Smile", "jp": "Romantic Smile", "zh_cn": "浪漫一笑"}, "known_as": []}, "namespace": ["track", "ost", "10"], "instance_id": "OST_10", "no": 10}}, "stats": {"is_ost": true, "is_ani": false, "is_short": false, "is_other": false, "is_ba": true, "is_jp": true, "is_global": true, "is_cn": true, "is_story": true, "is_story_main": true, "is_story_memory": true, "is_story_event": true, "is_battle": false, "is_battle_main": false, "is_battle_story": false, "is_battle_event": false, "is_segment": false, "is_sub": false, "has_related": false}}}}, "_track_to_bg": {"OST_9": ["BG_WaterFall.jpg"]}, "track_to_bg": {"OST_9": ["6bb2413f-8d3e-442c-95e1-906d99592f35"]}, "track_to_char": {"OST_9": ["Hanako_Swimsuit"]}, "bg_to_char": {"BG_WaterFall.jpg": ["Hanako_Swimsuit"]}, "bg_to_track": {"BG_WaterFall.jpg": ["OST_9"]}, "char_to_track": {"Hanako_Swimsuit": ["OST_9"]}, "_char_to_bg": {"Hanako_Swimsuit": ["BG_WaterFall.jpg"]}, "char_to_bg": {"Hanako_Swimsuit": ["6bb2413f-8d3e-442c-95e1-906d99592f35"]}, "char_to_char": {}, "special": {"flag": true, "track": {"uuid": "b6cd18b0-eae5-4f86-8bca-b943f184f9d5", "no": 9, "filetype": 1, "namespace": ["track", "ost", "9"], "track_type": 0, "instance_id": "OST_9", "name": {"realname": {"en": "Midsummer Cat", "jp": "Midsummer Cat", "zh_cn": "仲夏一猫"}, "known_as": []}, "desc": {"en": "【暂无】", "jp": "【暂无】", "zh_cn": "【暂无】"}, "composer": {"composer_id": "1", "nickname": "Mitsukiyo", "contact": {"platform": {"en": "Twitter", "jp": "Twitter", "zh_cn": "Twitter"}, "url": {"platform": {"en": "Twitter", "jp": "Twitter", "zh_cn": "Twitter"}, "value": "https://twitter.com/mitsukiyo_5", "short_desc": {"en": "", "jp": "", "zh_cn": ""}}}}, "tags": [{"uuid": "9ade045f-f24e-4f88-8af6-0458db3332ae", "filetype": 61, "name": {"en": "Relaxing", "jp": "Relaxing", "zh_cn": "轻松惬意"}, "desc": {"en": "Sometimes it's good to have a cup of tea and relaxed. <b>Example: Cherry Merry Berry</b>", "jp": "Sometimes it's good to have a cup of tea and relaxed. <b>Example: Cherry Merry Berry</b>", "zh_cn": "有些时候，停下来饮杯茶也不错。<b>举例/联想：Cherry Merry Berry</b>"}, "namespace": ["tag", "relaxing"], "color": "green", "color_css": "success", "interpage": {"prev": {"name": {"en": "Possibilities", "jp": "Possibilities", "zh_cn": "可能性"}, "namespace": ["tag", "possibilities"]}, "next": {"name": {"en": "Sad", "jp": "Sad", "zh_cn": "悲伤的"}, "namespace": ["tag", "sad"]}}}, {"uuid": "740e5356-bb52-4b4f-ab41-c62f6f5a6c09", "filetype": 61, "name": {"en": "Day to Day", "jp": "Day to Day", "zh_cn": "日常的"}, "desc": {"en": "Aside from all the ups and downs, we need some to to relax our mind. <b>Example: Lemonade Diary, Nesno wons.</b> Main characteristics are soft, gentle.", "jp": "Aside from all the ups and downs, we need some to to relax our mind. <b>Example: Lemonade Diary, Nesno wons.</b> Main characteristics are soft, gentle.", "zh_cn": "在大起大落的事情里外，我们总需要一点闲适的时间来放松自己的神经。<b>举例/联想：Lemonade Diary、Nesno wons；特征是较为温柔。</b>"}, "namespace": ["tag", "daytoday"], "color": "green", "color_css": "success", "interpage": {"prev": {"name": {"en": "Cheerful", "jp": "Cheerful", "zh_cn": "欢快"}, "namespace": ["tag", "cheerful"]}, "next": {"name": {"en": "Discouraged", "jp": "Discouraged", "zh_cn": "灰心的"}, "namespace": ["tag", "discouraged"]}}}], "image": {"platform": {"en": "None", "jp": "None", "zh_cn": "None"}, "value": "/static/images/background/BG_View_Kivotos.jpg", "short_desc": {"en": "", "jp": "", "zh_cn": ""}}, "album": [{"uuid": "80097a34-1ab3-4064-929a-ad18a2eecc36", "filetype": 5, "album_id": "01", "name": {"en": "Blue Archive Original Soundtrack (Vol.1 ~Longing for the memorable days~)", "jp": "Blue Archive Original Soundtrack (Vol.1 ~Longing for the memorable days~)", "zh_cn": "Blue Archive Original Soundtrack (Vol.1 ~Longing for the memorable days~)"}, "desc": {"en": "Blue Archive's first original soundtrack.", "jp": "Blue Archive's first original soundtrack.", "zh_cn": "Blue Archive's first original soundtrack."}, "namespace": ["album", "01"], "cover_img": "/static/images/album/01.png", "release_date": 1648080000, "release_date_format": "2022-03-24", "disc_num": 2, "track_num": 38}], "interpage": {"prev": {"name": {"realname": {"en": "Shady Girls", "jp": "Shady Girls", "zh_cn": "鬼鬼祟祟的女孩"}, "known_as": []}, "namespace": ["track", "ost", "8"], "instance_id": "OST_8", "no": 8}, "next": {"name": {"realname": {"en": "Romantic Smile", "jp": "Romantic Smile", "zh_cn": "浪漫一笑"}, "known_as": []}, "namespace": ["track", "ost", "10"], "instance_id": "OST_10", "no": 10}}, "stats": {"is_ost": true, "is_ani": false, "is_short": false, "is_other": false, "is_ba": true, "is_jp": true, "is_global": true, "is_cn": true, "is_story": true, "is_story_main": true, "is_story_memory": true, "is_story_event": true, "is_battle": false, "is_battle_main": false, "is_battle_story": false, "is_battle_event": false, "is_segment": false, "is_sub": false, "has_related": false}}}}, "is_memory": true, "source": {"en": [], "zh_tw": [], "zh_cn_cn": [], "zh_cn_jp": []}, "interpage": {"prev": {"name": {"en": "There's No Danger Today", "jp": "There's No Danger Today", "zh_cn": "今天并不危险"}, "namespace": ["character", "student", "hanako_swimsuit", "bond", "01"], "is_memory": false, "pos": {"student": "HANAKO_SWIMSUIT", "no": 1, "favor_rank": 2}}, "next": {"name": {"en": "Unexpectedly Clumsy", "jp": "Unexpectedly Clumsy", "zh_cn": "意外笨拙的一面"}, "namespace": ["character", "student", "hanako_swimsuit", "bond", "03"], "is_memory": false, "pos": {"student": "HANAKO_SWIMSUIT", "no": 3, "favor_rank": 5}}}, "bgm_special": [{"uuid": "b6cd18b0-eae5-4f86-8bca-b943f184f9d5", "no": 9, "filetype": 1, "namespace": ["track", "ost", "9"], "track_type": 0, "instance_id": "OST_9", "name": {"realname": {"en": "Midsummer Cat", "jp": "Midsummer Cat", "zh_cn": "仲夏一猫"}, "known_as": []}, "desc": {"en": "【暂无】", "jp": "【暂无】", "zh_cn": "【暂无】"}, "composer": {"composer_id": "1", "nickname": "Mitsukiyo", "contact": {"platform": {"en": "Twitter", "jp": "Twitter", "zh_cn": "Twitter"}, "url": {"platform": {"en": "Twitter", "jp": "Twitter", "zh_cn": "Twitter"}, "value": "https://twitter.com/mitsukiyo_5", "short_desc": {"en": "", "jp": "", "zh_cn": ""}}}}, "tags": [{"uuid": "9ade045f-f24e-4f88-8af6-0458db3332ae", "filetype": 61, "name": {"en": "Relaxing", "jp": "Relaxing", "zh_cn": "轻松惬意"}, "desc": {"en": "Sometimes it's good to have a cup of tea and relaxed. <b>Example: Cherry Merry Berry</b>", "jp": "Sometimes it's good to have a cup of tea and relaxed. <b>Example: Cherry Merry Berry</b>", "zh_cn": "有些时候，停下来饮杯茶也不错。<b>举例/联想：Cherry Merry Berry</b>"}, "namespace": ["tag", "relaxing"], "color": "green", "color_css": "success", "interpage": {"prev": {"name": {"en": "Possibilities", "jp": "Possibilities", "zh_cn": "可能性"}, "namespace": ["tag", "possibilities"]}, "next": {"name": {"en": "Sad", "jp": "Sad", "zh_cn": "悲伤的"}, "namespace": ["tag", "sad"]}}}, {"uuid": "740e5356-bb52-4b4f-ab41-c62f6f5a6c09", "filetype": 61, "name": {"en": "Day to Day", "jp": "Day to Day", "zh_cn": "日常的"}, "desc": {"en": "Aside from all the ups and downs, we need some to to relax our mind. <b>Example: Lemonade Diary, Nesno wons.</b> Main characteristics are soft, gentle.", "jp": "Aside from all the ups and downs, we need some to to relax our mind. <b>Example: Lemonade Diary, Nesno wons.</b> Main characteristics are soft, gentle.", "zh_cn": "在大起大落的事情里外，我们总需要一点闲适的时间来放松自己的神经。<b>举例/联想：Lemonade Diary、Nesno wons；特征是较为温柔。</b>"}, "namespace": ["tag", "daytoday"], "color": "green", "color_css": "success", "interpage": {"prev": {"name": {"en": "Cheerful", "jp": "Cheerful", "zh_cn": "欢快"}, "namespace": ["tag", "cheerful"]}, "next": {"name": {"en": "Discouraged", "jp": "Discouraged", "zh_cn": "灰心的"}, "namespace": ["tag", "discouraged"]}}}], "image": {"platform": {"en": "None", "jp": "None", "zh_cn": "None"}, "value": "/static/images/background/BG_View_Kivotos.jpg", "short_desc": {"en": "", "jp": "", "zh_cn": ""}}, "album": [{"uuid": "80097a34-1ab3-4064-929a-ad18a2eecc36", "filetype": 5, "album_id": "01", "name": {"en": "Blue Archive Original Soundtrack (Vol.1 ~Longing for the memorable days~)", "jp": "Blue Archive Original Soundtrack (Vol.1 ~Longing for the memorable days~)", "zh_cn": "Blue Archive Original Soundtrack (Vol.1 ~Longing for the memorable days~)"}, "desc": {"en": "Blue Archive's first original soundtrack.", "jp": "Blue Archive's first original soundtrack.", "zh_cn": "Blue Archive's first original soundtrack."}, "namespace": ["album", "01"], "cover_img": "/static/images/album/01.png", "release_date": 1648080000, "release_date_format": "2022-03-24", "disc_num": 2, "track_num": 38}], "interpage": {"prev": {"name": {"realname": {"en": "Shady Girls", "jp": "Shady Girls", "zh_cn": "鬼鬼祟祟的女孩"}, "known_as": []}, "namespace": ["track", "ost", "8"], "instance_id": "OST_8", "no": 8}, "next": {"name": {"realname": {"en": "Romantic Smile", "jp": "Romantic Smile", "zh_cn": "浪漫一笑"}, "known_as": []}, "namespace": ["track", "ost", "10"], "instance_id": "OST_10", "no": 10}}, "stats": {"is_ost": true, "is_ani": false, "is_short": false, "is_other": false, "is_ba": true, "is_jp": true, "is_global": true, "is_cn": true, "is_story": true, "is_story_main": true, "is_story_memory": true, "is_story_event": true, "is_battle": false, "is_battle_main": false, "is_battle_story": false, "is_battle_event": false, "is_segment": false, "is_sub": false, "has_related": false}}], "parent_data": null, "student": {"uuid": "Hanako_Swimsuit", "id": 10074, "name": {"path_name": "Hanako_Swimsuit", "dev_name": "CH0209", "family_name": {"en": "Urawa", "jp": "浦和", "zh_cn_jp": "浦和", "zh_cn_tw": "浦和", "zh_cn_cn": "浦和"}, "personal_name": {"en": "Hanako", "jp": "ハナコ", "zh_cn_jp": "花子", "zh_cn_tw": "花子", "zh_cn_cn": "花子"}, "name": {"en": "Hanako (Swimsuit)", "jp": "ハナコ（水着）", "zh_cn_jp": "花子（泳装）", "zh_cn_tw": "花子(泳装)", "zh_cn_cn": "花子（泳装）"}}, "image": {"collection_bg": "BG_WaterFall", "collection_texture": "10074"}, "birthday": {"localized": {"en": "January 3rd", "jp": "1月3日", "zh_cn_jp": "1月3日", "zh_cn_tw": "1月3日", "zh_cn_cn": "1月3日"}, "normalized": {"en": "1/3", "jp": "1/3", "zh_cn_jp": "1/3", "zh_cn_tw": "1/3", "zh_cn_cn": "1/3"}}, "school": {"short": {"en": "Trinity", "jp": "トリニティ", "zh_cn_jp": "三一", "zh_cn_tw": "三一", "zh_cn_cn": "崔尼蒂"}, "long": {"en": "Trinity General School", "jp": "トリニティ総合学園", "zh_cn_jp": "三一综合学园", "zh_cn_tw": "三一综合学园", "zh_cn_cn": "崔尼蒂综合学院"}}, "school_id": "Trinity", "club": {"en": "Make-Up Work Club", "jp": "補習授業部", "zh_cn_jp": "补课部", "zh_cn_tw": "补课部", "zh_cn_cn": "补习部"}, "age": {"en": "16 years old", "jp": "16歳", "zh_cn_jp": "16岁", "zh_cn_tw": "16岁", "zh_cn_cn": "16岁"}, "hobby": {"en": "Taking walks", "jp": "徘徊", "zh_cn_jp": "徘徊", "zh_cn_tw": "散步", "zh_cn_cn": "徘徊"}, "interpage": {"prev": {"name": {"path_name": "Hanako", "dev_name": "Hanako", "name": {"en": "Hanako", "jp": "ハナコ", "zh_cn_jp": "花子", "zh_cn_tw": "花子", "zh_cn_cn": "花子"}}, "namespace": ["character", "student", "hanako"]}, "next": {"name": {"path_name": "Hare", "dev_name": "Hare", "name": {"en": "Hare", "jp": "ハレ", "zh_cn_jp": "晴", "zh_cn_tw": "晴", "zh_cn_cn": "晴"}}, "namespace": ["character", "student", "hare"]}}, "combatant_info": {"squad_type": {"type": "Main", "lang": {"en": "STRIKER", "jp": "STRIKER", "zh_cn_jp": "前锋", "zh_cn_tw": "STRIKER", "zh_cn_cn": "突击"}}, "attack_type": {"type": "Sonic", "lang": {"en": "Sonic", "jp": "振動", "zh_cn_jp": "振动", "zh_cn_tw": "振动", "zh_cn_cn": "振动"}}, "armor_type": {"type": "HeavyArmor", "lang": {"en": "Heavy", "jp": "重装甲", "zh_cn_jp": "重型装甲", "zh_cn_tw": "重装甲", "zh_cn_cn": "重装甲"}}}, "bond_track": {"uuid": "b6cd18b0-eae5-4f86-8bca-b943f184f9d5", "no": 9, "filetype": 1, "namespace": ["track", "ost", "9"], "track_type": 0, "instance_id": "OST_9", "name": {"realname": {"en": "Midsummer Cat", "jp": "Midsummer Cat", "zh_cn": "仲夏一猫"}, "known_as": []}, "desc": {"en": "【暂无】", "jp": "【暂无】", "zh_cn": "【暂无】"}, "composer": {"composer_id": "1", "nickname": "Mitsukiyo", "contact": {"platform": {"en": "Twitter", "jp": "Twitter", "zh_cn": "Twitter"}, "url": {"platform": {"en": "Twitter", "jp": "Twitter", "zh_cn": "Twitter"}, "value": "https://twitter.com/mitsukiyo_5", "short_desc": {"en": "", "jp": "", "zh_cn": ""}}}}, "tags": [{"uuid": "9ade045f-f24e-4f88-8af6-0458db3332ae", "filetype": 61, "name": {"en": "Relaxing", "jp": "Relaxing", "zh_cn": "轻松惬意"}, "desc": {"en": "Sometimes it's good to have a cup of tea and relaxed. <b>Example: Cherry Merry Berry</b>", "jp": "Sometimes it's good to have a cup of tea and relaxed. <b>Example: Cherry Merry Berry</b>", "zh_cn": "有些时候，停下来饮杯茶也不错。<b>举例/联想：Cherry Merry Berry</b>"}, "namespace": ["tag", "relaxing"], "color": "green", "color_css": "success", "interpage": {"prev": {"name": {"en": "Possibilities", "jp": "Possibilities", "zh_cn": "可能性"}, "namespace": ["tag", "possibilities"]}, "next": {"name": {"en": "Sad", "jp": "Sad", "zh_cn": "悲伤的"}, "namespace": ["tag", "sad"]}}}, {"uuid": "740e5356-bb52-4b4f-ab41-c62f6f5a6c09", "filetype": 61, "name": {"en": "Day to Day", "jp": "Day to Day", "zh_cn": "日常的"}, "desc": {"en": "Aside from all the ups and downs, we need some to to relax our mind. <b>Example: Lemonade Diary, Nesno wons.</b> Main characteristics are soft, gentle.", "jp": "Aside from all the ups and downs, we need some to to relax our mind. <b>Example: Lemonade Diary, Nesno wons.</b> Main characteristics are soft, gentle.", "zh_cn": "在大起大落的事情里外，我们总需要一点闲适的时间来放松自己的神经。<b>举例/联想：Lemonade Diary、Nesno wons；特征是较为温柔。</b>"}, "namespace": ["tag", "daytoday"], "color": "green", "color_css": "success", "interpage": {"prev": {"name": {"en": "Cheerful", "jp": "Cheerful", "zh_cn": "欢快"}, "namespace": ["tag", "cheerful"]}, "next": {"name": {"en": "Discouraged", "jp": "Discouraged", "zh_cn": "灰心的"}, "namespace": ["tag", "discouraged"]}}}], "image": {"platform": {"en": "None", "jp": "None", "zh_cn": "None"}, "value": "/static/images/background/BG_View_Kivotos.jpg", "short_desc": {"en": "", "jp": "", "zh_cn": ""}}, "album": [{"uuid": "80097a34-1ab3-4064-929a-ad18a2eecc36", "filetype": 5, "album_id": "01", "name": {"en": "Blue Archive Original Soundtrack (Vol.1 ~Longing for the memorable days~)", "jp": "Blue Archive Original Soundtrack (Vol.1 ~Longing for the memorable days~)", "zh_cn": "Blue Archive Original Soundtrack (Vol.1 ~Longing for the memorable days~)"}, "desc": {"en": "Blue Archive's first original soundtrack.", "jp": "Blue Archive's first original soundtrack.", "zh_cn": "Blue Archive's first original soundtrack."}, "namespace": ["album", "01"], "cover_img": "/static/images/album/01.png", "release_date": 1648080000, "release_date_format": "2022-03-24", "disc_num": 2, "track_num": 38}], "interpage": {"prev": {"name": {"realname": {"en": "Shady Girls", "jp": "Shady Girls", "zh_cn": "鬼鬼祟祟的女孩"}, "known_as": []}, "namespace": ["track", "ost", "8"], "instance_id": "OST_8", "no": 8}, "next": {"name": {"realname": {"en": "Romantic Smile", "jp": "Romantic Smile", "zh_cn": "浪漫一笑"}, "known_as": []}, "namespace": ["track", "ost", "10"], "instance_id": "OST_10", "no": 10}}, "stats": {"is_ost": true, "is_ani": false, "is_short": false, "is_other": false, "is_ba": true, "is_jp": true, "is_global": true, "is_cn": true, "is_story": true, "is_story_main": true, "is_story_memory": true, "is_story_event": true, "is_battle": false, "is_battle_main": false, "is_battle_story": false, "is_battle_event": false, "is_segment": false, "is_sub": false, "has_related": false}}, "bond_rank": 3}}