{"uuid": "f27267dd-9859-41f7-800a-897b7a201e99", "filetype": 71, "filename": "BG_CS_Millenium_20.jpg", "name": {"en": "BG_CS_Millenium_20.jpg", "jp": "BG_CS_Millenium_20.jpg", "thai": "BG_CS_Millenium_20.jpg", "ko": "BG_CS_Millenium_20.jpg", "zh_cn": "BG_CS_Millenium_20.jpg", "zh_tw": "BG_CS_Millenium_20.jpg"}, "desc": {"en": "BG_CS_Millenium_20.jpg Description", "jp": "BG_CS_Millenium_20.jpg Description", "thai": "BG_CS_Millenium_20.jpg Description", "ko": "BG_CS_Millenium_20.jpg Description", "zh_cn": "BG_CS_Millenium_20.jpg Description", "zh_tw": "BG_CS_Millenium_20.jpg Description"}, "tag": [], "image": {"platform": {"en": "None", "jp": "None", "thai": "None", "ko": "None", "zh_cn": "None", "zh_tw": "None"}, "value": "/static/images/background/BG_CS_Millenium_20.jpg", "short_desc": ""}, "used_by": {"data_story": {}, "data_track": {}}, "interpage": {"prev": {"name": {"en": "BG_CS_Millenium_19.jpg", "jp": "BG_CS_Millenium_19.jpg", "thai": "BG_CS_Millenium_19.jpg", "ko": "BG_CS_Millenium_19.jpg", "zh_cn": "BG_CS_Millenium_19.jpg", "zh_tw": "BG_CS_Millenium_19.jpg"}, "namespace": ["background", "BG_CS_Millenium_19.jpg"]}, "next": {"name": {"en": "BG_CS_Millenium_21.jpg", "jp": "BG_CS_Millenium_21.jpg", "thai": "BG_CS_Millenium_21.jpg", "ko": "BG_CS_Millenium_21.jpg", "zh_cn": "BG_CS_Millenium_21.jpg", "zh_tw": "BG_CS_Millenium_21.jpg"}, "namespace": ["background", "BG_CS_Millenium_21.jpg"]}}}