{"uuid": "1eeb3f16-daf4-46ee-a248-1f9a38957777", "filetype": 71, "filename": "BG_ClassRoom2.jpg", "name": {"en": "BG_ClassRoom2.jpg", "jp": "BG_ClassRoom2.jpg", "thai": "BG_ClassRoom2.jpg", "ko": "BG_ClassRoom2.jpg", "zh_cn": "BG_ClassRoom2.jpg", "zh_tw": "BG_ClassRoom2.jpg"}, "desc": {"en": "BG_ClassRoom2.jpg Description", "jp": "BG_ClassRoom2.jpg Description", "thai": "BG_ClassRoom2.jpg Description", "ko": "BG_ClassRoom2.jpg Description", "zh_cn": "BG_ClassRoom2.jpg Description", "zh_tw": "BG_ClassRoom2.jpg Description"}, "tag": [], "image": {"platform": {"en": "None", "jp": "None", "thai": "None", "ko": "None", "zh_cn": "None", "zh_tw": "None"}, "value": "/static/images/background/BG_ClassRoom2.jpg", "short_desc": {"en": "", "jp": "", "thai": "", "ko": "", "zh_tw": "", "zh_cn_jp": "", "zh_cn_tw": "", "zh_cn_cn": ""}}, "used_by": {"data_story": {}, "data_track": {}, "data_character": {}}, "interpage": {"prev": {"name": {"en": "BG_ClassRoom.jpg", "jp": "BG_ClassRoom.jpg", "thai": "BG_ClassRoom.jpg", "ko": "BG_ClassRoom.jpg", "zh_cn": "BG_ClassRoom.jpg", "zh_tw": "BG_ClassRoom.jpg"}, "namespace": ["background", "BG_ClassRoom.jpg"]}, "next": {"name": {"en": "BG_ClassRoom2_Night.jpg", "jp": "BG_ClassRoom2_Night.jpg", "thai": "BG_ClassRoom2_Night.jpg", "ko": "BG_ClassRoom2_Night.jpg", "zh_cn": "BG_ClassRoom2_Night.jpg", "zh_tw": "BG_ClassRoom2_Night.jpg"}, "namespace": ["background", "BG_ClassRoom2_Night.jpg"]}}}