{"uuid": "7a292534-0f6c-4c2b-b42d-f7f9d2968662", "filetype": 71, "filename": "BG_CS_PV3_50_2.jpg", "name": {"en": "BG_CS_PV3_50_2.jpg", "jp": "BG_CS_PV3_50_2.jpg", "thai": "BG_CS_PV3_50_2.jpg", "ko": "BG_CS_PV3_50_2.jpg", "zh_cn": "BG_CS_PV3_50_2.jpg", "zh_tw": "BG_CS_PV3_50_2.jpg"}, "desc": {"en": "BG_CS_PV3_50_2.jpg Description", "jp": "BG_CS_PV3_50_2.jpg Description", "thai": "BG_CS_PV3_50_2.jpg Description", "ko": "BG_CS_PV3_50_2.jpg Description", "zh_cn": "BG_CS_PV3_50_2.jpg Description", "zh_tw": "BG_CS_PV3_50_2.jpg Description"}, "tag": [], "image": {"platform": {"en": "None", "jp": "None", "thai": "None", "ko": "None", "zh_cn": "None", "zh_tw": "None"}, "value": "/static/images/background/BG_CS_PV3_50_2.jpg", "short_desc": ""}, "used_by": {"data_story": {}, "data_track": {}}, "interpage": {"prev": {"name": {"en": "BG_CS_PV3_50.jpg", "jp": "BG_CS_PV3_50.jpg", "thai": "BG_CS_PV3_50.jpg", "ko": "BG_CS_PV3_50.jpg", "zh_cn": "BG_CS_PV3_50.jpg", "zh_tw": "BG_CS_PV3_50.jpg"}, "namespace": ["background", "BG_CS_PV3_50.jpg"]}, "next": {"name": {"en": "BG_CS_PV3_51.jpg", "jp": "BG_CS_PV3_51.jpg", "thai": "BG_CS_PV3_51.jpg", "ko": "BG_CS_PV3_51.jpg", "zh_cn": "BG_CS_PV3_51.jpg", "zh_tw": "BG_CS_PV3_51.jpg"}, "namespace": ["background", "BG_CS_PV3_51.jpg"]}}}