{"uuid": "106b0257-48f2-414e-a6d6-415795a649bf", "filetype": 71, "filename": "BG_EriduTowerRooftop_Night.jpg", "name": {"en": "BG_EriduTowerRooftop_Night.jpg", "jp": "BG_EriduTowerRooftop_Night.jpg", "thai": "BG_EriduTowerRooftop_Night.jpg", "ko": "BG_EriduTowerRooftop_Night.jpg", "zh_cn": "BG_EriduTowerRooftop_Night.jpg", "zh_tw": "BG_EriduTowerRooftop_Night.jpg"}, "desc": {"en": "BG_EriduTowerRooftop_Night.jpg Description", "jp": "BG_EriduTowerRooftop_Night.jpg Description", "thai": "BG_EriduTowerRooftop_Night.jpg Description", "ko": "BG_EriduTowerRooftop_Night.jpg Description", "zh_cn": "BG_EriduTowerRooftop_Night.jpg Description", "zh_tw": "BG_EriduTowerRooftop_Night.jpg Description"}, "tag": [], "image": {"platform": {"en": "None", "jp": "None", "thai": "None", "ko": "None", "zh_cn": "None", "zh_tw": "None"}, "value": "/static/images/background/BG_EriduTowerRooftop_Night.jpg", "short_desc": ""}, "used_by": {"data_story": {}, "data_track": {}}, "interpage": {"prev": {"name": {"en": "BG_EriduTowerRooftop.jpg", "jp": "BG_EriduTowerRooftop.jpg", "thai": "BG_EriduTowerRooftop.jpg", "ko": "BG_EriduTowerRooftop.jpg", "zh_cn": "BG_EriduTowerRooftop.jpg", "zh_tw": "BG_EriduTowerRooftop.jpg"}, "namespace": ["background", "BG_EriduTowerRooftop.jpg"]}, "next": {"name": {"en": "BG_FamilyRestaurant.jpg", "jp": "BG_FamilyRestaurant.jpg", "thai": "BG_FamilyRestaurant.jpg", "ko": "BG_FamilyRestaurant.jpg", "zh_cn": "BG_FamilyRestaurant.jpg", "zh_tw": "BG_FamilyRestaurant.jpg"}, "namespace": ["background", "BG_FamilyRestaurant.jpg"]}}}