{"uuid": "198fb21c-9dd2-4bf3-9fa7-e3847acb044b", "filetype": 71, "filename": "BG_RailWayCrossing.jpg", "name": {"en": "BG_RailWayCrossing.jpg", "jp": "BG_RailWayCrossing.jpg", "thai": "BG_RailWayCrossing.jpg", "ko": "BG_RailWayCrossing.jpg", "zh_cn": "BG_RailWayCrossing.jpg", "zh_tw": "BG_RailWayCrossing.jpg"}, "desc": {"en": "BG_RailWayCrossing.jpg Description", "jp": "BG_RailWayCrossing.jpg Description", "thai": "BG_RailWayCrossing.jpg Description", "ko": "BG_RailWayCrossing.jpg Description", "zh_cn": "BG_RailWayCrossing.jpg Description", "zh_tw": "BG_RailWayCrossing.jpg Description"}, "tag": [], "image": {"platform": {"en": "None", "jp": "None", "thai": "None", "ko": "None", "zh_cn": "None", "zh_tw": "None"}, "value": "/static/images/background/BG_RailWayCrossing.jpg", "short_desc": {"en": "", "jp": "", "thai": "", "ko": "", "zh_tw": "", "zh_cn_jp": "", "zh_cn_tw": "", "zh_cn_cn": ""}}, "used_by": {"data_story": {}, "data_track": {}}, "interpage": {"prev": {"name": {"en": "BG_CS_PV2_68.jpg", "jp": "BG_CS_PV2_68.jpg", "thai": "BG_CS_PV2_68.jpg", "ko": "BG_CS_PV2_68.jpg", "zh_cn": "BG_CS_PV2_68.jpg", "zh_tw": "BG_CS_PV2_68.jpg"}, "namespace": ["background", "BG_CS_PV2_68.jpg"]}, "next": {"name": {"en": "BG_CS_PV4_013_2.jpg", "jp": "BG_CS_PV4_013_2.jpg", "thai": "BG_CS_PV4_013_2.jpg", "ko": "BG_CS_PV4_013_2.jpg", "zh_cn": "BG_CS_PV4_013_2.jpg", "zh_tw": "BG_CS_PV4_013_2.jpg"}, "namespace": ["background", "BG_CS_PV4_013_2.jpg"]}}}