{"uuid": "24a07d9a-eff7-4734-9ab5-7a509ca36b6d", "filetype": 15, "filetype_sub": 1, "namespace": ["character", "student", "ako", "bond", "01"], "name": {"en": "總之就是陰謀！", "jp": "總之就是陰謀！", "zh_cn": "总之就是阴谋！"}, "desc": [{"en": "亞子約老師見面，想一起討論夏萊的可疑之處。老師身為夏萊的一分子雖然感到有些不知所措，但亞子卻興奮地告訴老師除了夏萊以外，奇普托斯之中還有許多對風紀委員會虎視眈眈的危險勢力。之後亞子恢復了理智，急忙逃離了現場。", "jp": "亞子約老師見面，想一起討論夏萊的可疑之處。老師身為夏萊的一分子雖然感到有些不知所措，但亞子卻興奮地告訴老師除了夏萊以外，奇普托斯之中還有許多對風紀委員會虎視眈眈的危險勢力。之後亞子恢復了理智，急忙逃離了現場。", "zh_cn": "亚子约老师见面，想一起讨论夏莱的可疑之处。老师身为夏莱的一分子虽然感到有些不知所措，但亚子却兴奋地告诉老师除了夏莱以外，奇普托斯之中还有许多对风纪委员会虎视眈眈的危险势力。之后亚子恢复了理智，急忙逃离了现场。"}], "pos": {"student": "AKO", "no": 1, "favor_rank": 2}, "image": {"platform": -1, "value": "", "short_desc": ""}, "instance_id": "BOND_AKO_1_2", "part": {"all": {"background": {"BG_ModernCafe.jpg": {"uuid": "58500ade-32d3-416f-aa19-cd24432131c9", "filetype": 71, "filename": "BG_ModernCafe.jpg", "name": {"en": "BG_ModernCafe.jpg", "jp": "BG_ModernCafe.jpg", "zh_cn": "BG_ModernCafe.jpg"}, "desc": {"en": "BG_ModernCafe.jpg Description", "jp": "BG_ModernCafe.jpg Description", "zh_cn": "BG_ModernCafe.jpg Description"}, "image": {"platform": {"en": "None", "jp": "None", "zh_cn": "None"}, "value": "/static/images/background/BG_ModernCafe.jpg", "short_desc": {"en": "", "jp": "", "zh_cn": ""}}, "character": [], "interpage": {"prev": {"name": {"en": "BG_MissileSilo_Night.jpg", "jp": "BG_MissileSilo_Night.jpg", "zh_cn": "BG_MissileSilo_Night.jpg"}, "namespace": ["background", "BG_MissileSilo_Night.jpg"]}, "next": {"name": {"en": "BG_MudFlat.jpg", "jp": "BG_MudFlat.jpg", "zh_cn": "BG_MudFlat.jpg"}, "namespace": ["background", "BG_MudFlat.jpg"]}}}}, "character": {"Ako": {"uuid": "Ako", "id": 20008, "name": {"path_name": "Ako", "dev_name": "Ako", "family_name": {"en": "Amau", "jp": "天雨", "zh_cn_jp": "天雨", "zh_cn_tw": "天雨", "zh_cn_cn": "天雨"}, "personal_name": {"en": "Ako", "jp": "アコ", "zh_cn_jp": "亚子", "zh_cn_tw": "亚子", "zh_cn_cn": "亚子"}, "name": {"en": "Ako", "jp": "アコ", "zh_cn_jp": "亚子", "zh_cn_tw": "亚子", "zh_cn_cn": "亚子"}}, "image": {"collection_bg": "BG_Gehenna_Collection", "collection_texture": "20008"}, "birthday": {"localized": {"en": "December 22nd", "jp": "12月22日", "zh_cn_jp": "12月22日", "zh_cn_tw": "12月22日", "zh_cn_cn": "12月22日"}, "normalized": {"en": "12/22", "jp": "12/22", "zh_cn_jp": "12/22", "zh_cn_tw": "12/22", "zh_cn_cn": "12/22"}}, "school": {"short": {"en": "Gehenna", "jp": "ゲヘナ", "zh_cn_jp": "格黑娜", "zh_cn_tw": "格黑娜", "zh_cn_cn": "歌赫娜"}, "long": {"en": "Gehenna Academy", "jp": "ゲヘナ学園", "zh_cn_jp": "格黑娜学园", "zh_cn_tw": "格黑娜学园", "zh_cn_cn": "歌赫娜学院"}}, "school_id": "Gehenna", "club": {"en": "Prefect Team", "jp": "風紀委員会", "zh_cn_jp": "风纪委员会", "zh_cn_tw": "风纪委员会", "zh_cn_cn": "风纪委员会"}, "age": {"en": "17 years old", "jp": "17歳", "zh_cn_jp": "17岁", "zh_cn_tw": "17岁", "zh_cn_cn": "17岁"}, "hobby": {"en": "Hina", "jp": "ヒナ委員長", "zh_cn_jp": "日奈委员长", "zh_cn_tw": "阳奈委员长", "zh_cn_cn": "日奈"}, "interpage": {"prev": {"name": {"path_name": "Akari", "dev_name": "Akari", "name": {"en": "Akari", "jp": "アカリ", "zh_cn_jp": "明里", "zh_cn_tw": "亚伽里", "zh_cn_cn": "明里"}}, "namespace": ["character", "student", "akari"]}, "next": {"name": {"path_name": "Ako_Dress", "dev_name": "CH0231", "name": {"en": "Ako (Dress)", "jp": "アコ（ドレス）", "zh_cn_jp": "亚子（礼服）", "zh_cn_tw": "アコ（ドレス）", "zh_cn_cn": "亚子（礼服）"}}, "namespace": ["character", "student", "ako_dress"]}}, "combatant_info": {"squad_type": {"type": "Support", "lang": {"en": "SPECIAL", "jp": "SPECIAL", "zh_cn_jp": "后援", "zh_cn_tw": "SPECIAL", "zh_cn_cn": "支援"}}, "attack_type": {"type": "Mystic", "lang": {"en": "Mystic", "jp": "神秘", "zh_cn_jp": "神秘", "zh_cn_tw": "神秘", "zh_cn_cn": "神秘"}}, "armor_type": {"type": "HeavyArmor", "lang": {"en": "Heavy", "jp": "重装甲", "zh_cn_jp": "重型装甲", "zh_cn_tw": "重装甲", "zh_cn_cn": "重装甲"}}}, "bond_track": {"uuid": "8052c9c9-6f7a-4db3-b362-d729cc89fe6e", "no": 38, "filetype": 1, "namespace": ["track", "ost", "38"], "track_type": 0, "instance_id": "OST_38", "name": {"realname": {"en": "Guruguru Usagi", "jp": "Guruguru Usagi", "zh_cn": "Guruguru Usagi"}, "known_as": []}, "desc": {"en": "【暂无】", "jp": "【暂无】", "zh_cn": "【暂无】"}, "composer": {"composer_id": "1", "nickname": "Mitsukiyo", "contact": {"platform": {"en": "Twitter", "jp": "Twitter", "zh_cn": "Twitter"}, "url": {"platform": {"en": "Twitter", "jp": "Twitter", "zh_cn": "Twitter"}, "value": "https://twitter.com/mitsukiyo_5", "short_desc": {"en": "", "jp": "", "zh_cn": ""}}}}, "tags": [], "image": {"platform": {"en": "None", "jp": "None", "zh_cn": "None"}, "value": "/static/images/background/BG_View_Kivotos.jpg", "short_desc": {"en": "", "jp": "", "zh_cn": ""}}, "album": [], "interpage": {"prev": {"name": {"realname": {"en": "Aira", "jp": "Aira", "zh_cn": "Aira"}, "known_as": []}, "namespace": ["track", "ost", "37"], "instance_id": "OST_37", "no": 37}, "next": {"name": {"realname": {"en": "Water Drop", "jp": "Water Drop", "zh_cn": "一滴水"}, "known_as": []}, "namespace": ["track", "ost", "39"], "instance_id": "OST_39", "no": 39}}, "stats": {"is_ost": true, "is_ani": false, "is_short": false, "is_other": false, "is_ba": true, "is_jp": true, "is_global": true, "is_cn": true, "is_story": true, "is_story_main": true, "is_story_memory": true, "is_story_event": true, "is_battle": false, "is_battle_main": false, "is_battle_story": false, "is_battle_event": false, "is_segment": false, "is_sub": false, "has_related": false}}, "bond_rank": 5}}, "track": {"OST_16": {"uuid": "cbc90419-5bb0-4198-99e1-be1ca8d9dff8", "no": 16, "filetype": 1, "namespace": ["track", "ost", "16"], "track_type": 0, "instance_id": "OST_16", "name": {"realname": {"en": "MX Adventure", "jp": "MX Adventure", "zh_cn": "未知的冒险"}, "known_as": []}, "desc": {"en": "【暂无】", "jp": "【暂无】", "zh_cn": "【暂无】"}, "composer": {"composer_id": "1", "nickname": "Mitsukiyo", "contact": {"platform": {"en": "Twitter", "jp": "Twitter", "zh_cn": "Twitter"}, "url": {"platform": {"en": "Twitter", "jp": "Twitter", "zh_cn": "Twitter"}, "value": "https://twitter.com/mitsukiyo_5", "short_desc": {"en": "", "jp": "", "zh_cn": ""}}}}, "tags": [{"uuid": "d302c4cf-eb23-42b6-af20-86110b9fb7f2", "filetype": 61, "name": {"en": "Possibilities", "jp": "Possibilities", "zh_cn": "可能性"}, "desc": {"en": "Wait, what's gonna happen?! <b>Example: Theme 137</b>", "jp": "Wait, what's gonna happen?! <b>Example: Theme 137</b>", "zh_cn": "等下，接下来要发生什么？！<b>举例：第137首曲子</b>"}, "namespace": ["tag", "possibilities"], "color": "blue", "color_css": "primary", "interpage": {"prev": {"name": {"en": "Nervous", "jp": "Nervous", "zh_cn": "紧张的"}, "namespace": ["tag", "nervous"]}, "next": {"name": {"en": "Relaxing", "jp": "Relaxing", "zh_cn": "轻松惬意"}, "namespace": ["tag", "relaxing"]}}}, {"uuid": "bfcb9f51-d989-4470-afd9-6fa490345920", "filetype": 61, "name": {"en": "Cheerful", "jp": "Cheerful", "zh_cn": "欢快"}, "desc": {"en": "<b>Example: Lovely Picnic</b>", "jp": "<b>Example: Lovely Picnic</b>", "zh_cn": "<b>举例/联想：Lovely Picnic</b>"}, "namespace": ["tag", "cheerful"], "color": "green", "color_css": "success", "interpage": {"prev": {"name": {"en": "Chaos", "jp": "Chaos", "zh_cn": "混乱"}, "namespace": ["tag", "chaos"]}, "next": {"name": {"en": "Day to Day", "jp": "Day to Day", "zh_cn": "日常的"}, "namespace": ["tag", "daytoday"]}}}], "image": {"platform": {"en": "None", "jp": "None", "zh_cn": "None"}, "value": "/static/images/background/BG_View_Kivotos.jpg", "short_desc": {"en": "", "jp": "", "zh_cn": ""}}, "album": [{"uuid": "80097a34-1ab3-4064-929a-ad18a2eecc36", "filetype": 5, "album_id": "01", "name": {"en": "Blue Archive Original Soundtrack (Vol.1 ~Longing for the memorable days~)", "jp": "Blue Archive Original Soundtrack (Vol.1 ~Longing for the memorable days~)", "zh_cn": "Blue Archive Original Soundtrack (Vol.1 ~Longing for the memorable days~)"}, "desc": {"en": "Blue Archive's first original soundtrack.", "jp": "Blue Archive's first original soundtrack.", "zh_cn": "Blue Archive's first original soundtrack."}, "namespace": ["album", "01"], "cover_img": "/static/images/album/01.png", "release_date": 1648080000, "release_date_format": "2022-03-24", "disc_num": 2, "track_num": 38}], "interpage": {"prev": {"name": {"realname": {"en": "Honey Jam", "jp": "Honey Jam", "zh_cn": "蜂蜜果酱"}, "known_as": []}, "namespace": ["track", "ost", "15"], "instance_id": "OST_15", "no": 15}, "next": {"name": {"realname": {"en": "Irasshaimase", "jp": "Irasshaimase", "zh_cn": "欢迎光临"}, "known_as": []}, "namespace": ["track", "ost", "17"], "instance_id": "OST_17", "no": 17}}, "stats": {"is_ost": true, "is_ani": false, "is_short": false, "is_other": false, "is_ba": true, "is_jp": true, "is_global": true, "is_cn": true, "is_story": true, "is_story_main": true, "is_story_memory": false, "is_story_event": true, "is_battle": false, "is_battle_main": false, "is_battle_story": false, "is_battle_event": false, "is_segment": false, "is_sub": false, "has_related": false}}, "OST_10": {"uuid": "4c92dbd7-268e-400b-ad32-73ecb9e2ec99", "no": 10, "filetype": 1, "namespace": ["track", "ost", "10"], "track_type": 0, "instance_id": "OST_10", "name": {"realname": {"en": "Romantic Smile", "jp": "Romantic Smile", "zh_cn": "浪漫一笑"}, "known_as": []}, "desc": {"en": "The 10th track in Blue Archive, used in relationship stories majorly.", "jp": "The 10th track in Blue Archive, used in relationship stories majorly.", "zh_cn": "蔚蓝档案OST中的第十首曲子，主要用于羁绊故事中。"}, "composer": {"composer_id": "1", "nickname": "Mitsukiyo", "contact": {"platform": {"en": "Twitter", "jp": "Twitter", "zh_cn": "Twitter"}, "url": {"platform": {"en": "Twitter", "jp": "Twitter", "zh_cn": "Twitter"}, "value": "https://twitter.com/mitsukiyo_5", "short_desc": {"en": "", "jp": "", "zh_cn": ""}}}}, "tags": [{"uuid": "426d6221-67e7-40b5-b2af-1cae876201b7", "filetype": 61, "name": {"en": "Bright", "jp": "Bright", "zh_cn": "光明的"}, "desc": {"en": "In Kivotos, no future is dark; even so, it was temporary, as it will point to the bright ending that is possible to reach. <b>Example: Connected Sky, <i>Does the color of the sky mean anything special to you?</i></b>", "jp": "In Kivotos, no future is dark; even so, it was temporary, as it will point to the bright ending that is possible to reach. <b>Example: Connected Sky, <i>Does the color of the sky mean anything special to you?</i></b>", "zh_cn": "在基沃托斯，没有任何一个未来是黑暗的；即使有，那也只是暂时的，因为最终这一切都将指向光明，而那光明并非遥不可及。<b>举例/联想：Connected Sky，<i>Does the color of the sky mean anything special to you?</i></b>"}, "namespace": ["tag", "bright"], "color": "green", "color_css": "success", "interpage": {"prev": {"name": "[NO_PREV]", "namespace": "[NO_PREV]"}, "next": {"name": {"en": "Chaos", "jp": "Chaos", "zh_cn": "混乱"}, "namespace": ["tag", "chaos"]}}}, {"uuid": "3e5490bb-1dab-4316-a597-23a7a2e8e62c", "filetype": 61, "name": {"en": "Hopeful", "jp": "Hopeful", "zh_cn": "充满希望的"}, "desc": {"en": "Just do it! <b>Example: ystem All Green</b>", "jp": "Just do it! <b>Example: ystem All Green</b>", "zh_cn": "干就完了，奥利给！<b>举例/联想：System All Green</b>"}, "namespace": ["tag", "hopeful"], "color": "blue", "color_css": "primary", "interpage": {"prev": {"name": {"en": "Holy", "jp": "Holy", "zh_cn": "神圣的"}, "namespace": ["tag", "holy"]}, "next": {"name": {"en": "Mysterious", "jp": "Mysterious", "zh_cn": "神秘的"}, "namespace": ["tag", "mysterious"]}}}, {"uuid": "5b6663fb-8775-48d6-84df-e8a4b5c87d85", "filetype": 61, "name": {"en": "Dream", "jp": "Dream", "zh_cn": "梦想"}, "desc": {"en": "<b>Example: Aoharu</b>", "jp": "<b>Example: Aoharu</b>", "zh_cn": "<b>举例/联想：Aoharu</b>"}, "namespace": ["tag", "dream"], "color": "blue", "color_css": "primary", "interpage": {"prev": {"name": {"en": "Discouraged", "jp": "Discouraged", "zh_cn": "灰心的"}, "namespace": ["tag", "discouraged"]}, "next": {"name": {"en": "Emergency", "jp": "Emergency", "zh_cn": "紧急"}, "namespace": ["tag", "emergency"]}}}, {"uuid": "f6769f55-9d0a-4bc3-adf5-31d478e77720", "filetype": 61, "name": {"en": "Future", "jp": "Future", "zh_cn": "未来"}, "desc": {"en": "<b>Example: Aoharu</b>", "jp": "<b>Example: Aoharu</b>", "zh_cn": "<b>举例/联想：Aoharu</b>"}, "namespace": ["tag", "future"], "color": "blue", "color_css": "primary", "interpage": {"prev": {"name": {"en": "Failure", "jp": "Failure", "zh_cn": "失败"}, "namespace": ["tag", "failure"]}, "next": {"name": {"en": "Gloomy", "jp": "Gloomy", "zh_cn": "阴森的"}, "namespace": ["tag", "gloomy"]}}}, {"uuid": "bfcb9f51-d989-4470-afd9-6fa490345920", "filetype": 61, "name": {"en": "Cheerful", "jp": "Cheerful", "zh_cn": "欢快"}, "desc": {"en": "<b>Example: Lovely Picnic</b>", "jp": "<b>Example: Lovely Picnic</b>", "zh_cn": "<b>举例/联想：Lovely Picnic</b>"}, "namespace": ["tag", "cheerful"], "color": "green", "color_css": "success", "interpage": {"prev": {"name": {"en": "Chaos", "jp": "Chaos", "zh_cn": "混乱"}, "namespace": ["tag", "chaos"]}, "next": {"name": {"en": "Day to Day", "jp": "Day to Day", "zh_cn": "日常的"}, "namespace": ["tag", "daytoday"]}}}], "image": {"platform": {"en": "None", "jp": "None", "zh_cn": "None"}, "value": "/static/images/background/BG_View_Kivotos.jpg", "short_desc": {"en": "", "jp": "", "zh_cn": ""}}, "album": [], "interpage": {"prev": {"name": {"realname": {"en": "Midsummer Cat", "jp": "Midsummer Cat", "zh_cn": "仲夏一猫"}, "known_as": []}, "namespace": ["track", "ost", "9"], "instance_id": "OST_9", "no": 9}, "next": {"name": {"realname": {"en": "Connected Sky", "jp": "Connected Sky", "zh_cn": "共同的天空"}, "known_as": []}, "namespace": ["track", "ost", "11"], "instance_id": "OST_11", "no": 11}}, "stats": {"is_ost": true, "is_ani": false, "is_short": false, "is_other": false, "is_ba": true, "is_jp": true, "is_global": true, "is_cn": true, "is_story": true, "is_story_main": true, "is_story_memory": false, "is_story_event": true, "is_battle": false, "is_battle_main": false, "is_battle_story": false, "is_battle_event": false, "is_segment": false, "is_sub": false, "has_related": false}}, "OST_3": {"uuid": "adac9a1e-12b2-45ab-b2e6-192d421dbca2", "no": 3, "filetype": 1, "namespace": ["track", "ost", "3"], "track_type": 0, "instance_id": "OST_3", "name": {"realname": {"en": "Mischievous Step", "jp": "Mischievous Step", "zh_cn": "不定的步伐"}, "known_as": []}, "desc": {"en": "【暂无】", "jp": "【暂无】", "zh_cn": "【暂无】"}, "composer": {"composer_id": "1", "nickname": "Mitsukiyo", "contact": {"platform": {"en": "Twitter", "jp": "Twitter", "zh_cn": "Twitter"}, "url": {"platform": {"en": "Twitter", "jp": "Twitter", "zh_cn": "Twitter"}, "value": "https://twitter.com/mitsukiyo_5", "short_desc": {"en": "", "jp": "", "zh_cn": ""}}}}, "tags": [{"uuid": "9ade045f-f24e-4f88-8af6-0458db3332ae", "filetype": 61, "name": {"en": "Relaxing", "jp": "Relaxing", "zh_cn": "轻松惬意"}, "desc": {"en": "Sometimes it's good to have a cup of tea and relaxed. <b>Example: Cherry Merry Berry</b>", "jp": "Sometimes it's good to have a cup of tea and relaxed. <b>Example: Cherry Merry Berry</b>", "zh_cn": "有些时候，停下来饮杯茶也不错。<b>举例/联想：Cherry Merry Berry</b>"}, "namespace": ["tag", "relaxing"], "color": "green", "color_css": "success", "interpage": {"prev": {"name": {"en": "Possibilities", "jp": "Possibilities", "zh_cn": "可能性"}, "namespace": ["tag", "possibilities"]}, "next": {"name": {"en": "Sad", "jp": "Sad", "zh_cn": "悲伤的"}, "namespace": ["tag", "sad"]}}}, {"uuid": "7bfdc0c0-f08d-46c5-bee7-98f0a8f7d259", "filetype": 61, "name": {"en": "Naughty", "jp": "Naughty", "zh_cn": "调皮的"}, "desc": {"en": "<b>Example: Usagi Flap, Theme 114, Theme 159</b>", "jp": "<b>Example: Usagi Flap, Theme 114, Theme 159</b>", "zh_cn": "<b>举例/联想：Usagi Flap、第114首曲子、第159首曲子</b>"}, "namespace": ["tag", "naughty"], "color": "blue", "color_css": "primary", "interpage": {"prev": {"name": {"en": "Mysterious", "jp": "Mysterious", "zh_cn": "神秘的"}, "namespace": ["tag", "mysterious"]}, "next": {"name": {"en": "Nervous", "jp": "Nervous", "zh_cn": "紧张的"}, "namespace": ["tag", "nervous"]}}}], "image": {"platform": {"en": "None", "jp": "None", "zh_cn": "None"}, "value": "/static/images/background/BG_View_Kivotos.jpg", "short_desc": {"en": "", "jp": "", "zh_cn": ""}}, "album": [{"uuid": "80097a34-1ab3-4064-929a-ad18a2eecc36", "filetype": 5, "album_id": "01", "name": {"en": "Blue Archive Original Soundtrack (Vol.1 ~Longing for the memorable days~)", "jp": "Blue Archive Original Soundtrack (Vol.1 ~Longing for the memorable days~)", "zh_cn": "Blue Archive Original Soundtrack (Vol.1 ~Longing for the memorable days~)"}, "desc": {"en": "Blue Archive's first original soundtrack.", "jp": "Blue Archive's first original soundtrack.", "zh_cn": "Blue Archive's first original soundtrack."}, "namespace": ["album", "01"], "cover_img": "/static/images/album/01.png", "release_date": 1648080000, "release_date_format": "2022-03-24", "disc_num": 2, "track_num": 38}], "interpage": {"prev": {"name": {"realname": {"en": "Luminous Memory", "jp": "Luminous Memory", "zh_cn": "闪亮的记忆"}, "known_as": []}, "namespace": ["track", "ost", "2"], "instance_id": "OST_2", "no": 2}, "next": {"name": {"realname": {"en": "Lovely Picnic", "jp": "Lovely Picnic", "zh_cn": "美好的野餐"}, "known_as": []}, "namespace": ["track", "ost", "4"], "instance_id": "OST_4", "no": 4}}, "stats": {"is_ost": true, "is_ani": false, "is_short": false, "is_other": false, "is_ba": true, "is_jp": true, "is_global": true, "is_cn": true, "is_story": true, "is_story_main": true, "is_story_memory": false, "is_story_event": true, "is_battle": false, "is_battle_main": false, "is_battle_story": false, "is_battle_event": false, "is_segment": false, "is_sub": false, "has_related": false}}}}, "_track_to_bg": {"OST_16": ["BG_ModernCafe.jpg"], "OST_10": ["BG_ModernCafe.jpg"], "OST_3": ["BG_ModernCafe.jpg"]}, "track_to_bg": {"OST_16": ["58500ade-32d3-416f-aa19-cd24432131c9"], "OST_10": ["58500ade-32d3-416f-aa19-cd24432131c9"], "OST_3": ["58500ade-32d3-416f-aa19-cd24432131c9"]}, "track_to_char": {"OST_16": ["Ako"], "OST_10": ["Ako"], "OST_3": ["Ako"]}, "bg_to_char": {"BG_ModernCafe.jpg": ["Ako"]}, "bg_to_track": {"BG_ModernCafe.jpg": ["OST_16", "OST_10", "OST_3"]}, "char_to_track": {"Ako": ["OST_16", "OST_10", "OST_3"]}, "_char_to_bg": {"Ako": ["BG_ModernCafe.jpg"]}, "char_to_bg": {"Ako": ["58500ade-32d3-416f-aa19-cd24432131c9"]}, "char_to_char": {}, "special": {"flag": false, "track": null}}, "is_memory": false, "source": {"en": [], "zh_tw": [], "zh_cn_cn": [], "zh_cn_jp": []}, "interpage": {"prev": {"name": "[NO_PREV]", "namespace": "[NO_PREV]", "is_memory": "[NO_PREV]", "pos": "[NO_PREV]"}, "next": {"name": {"en": "總之就是急事！", "jp": "總之就是急事！", "zh_cn": "总之就是急事！"}, "namespace": ["character", "student", "ako", "bond", "02"], "is_memory": false, "pos": {"student": "AKO", "no": 2, "favor_rank": 3}}}, "parent_data": null, "student": {"uuid": "Ako", "id": 20008, "name": {"path_name": "Ako", "dev_name": "Ako", "family_name": {"en": "Amau", "jp": "天雨", "zh_cn_jp": "天雨", "zh_cn_tw": "天雨", "zh_cn_cn": "天雨"}, "personal_name": {"en": "Ako", "jp": "アコ", "zh_cn_jp": "亚子", "zh_cn_tw": "亚子", "zh_cn_cn": "亚子"}, "name": {"en": "Ako", "jp": "アコ", "zh_cn_jp": "亚子", "zh_cn_tw": "亚子", "zh_cn_cn": "亚子"}}, "image": {"collection_bg": "BG_Gehenna_Collection", "collection_texture": "20008"}, "birthday": {"localized": {"en": "December 22nd", "jp": "12月22日", "zh_cn_jp": "12月22日", "zh_cn_tw": "12月22日", "zh_cn_cn": "12月22日"}, "normalized": {"en": "12/22", "jp": "12/22", "zh_cn_jp": "12/22", "zh_cn_tw": "12/22", "zh_cn_cn": "12/22"}}, "school": {"short": {"en": "Gehenna", "jp": "ゲヘナ", "zh_cn_jp": "格黑娜", "zh_cn_tw": "格黑娜", "zh_cn_cn": "歌赫娜"}, "long": {"en": "Gehenna Academy", "jp": "ゲヘナ学園", "zh_cn_jp": "格黑娜学园", "zh_cn_tw": "格黑娜学园", "zh_cn_cn": "歌赫娜学院"}}, "school_id": "Gehenna", "club": {"en": "Prefect Team", "jp": "風紀委員会", "zh_cn_jp": "风纪委员会", "zh_cn_tw": "风纪委员会", "zh_cn_cn": "风纪委员会"}, "age": {"en": "17 years old", "jp": "17歳", "zh_cn_jp": "17岁", "zh_cn_tw": "17岁", "zh_cn_cn": "17岁"}, "hobby": {"en": "Hina", "jp": "ヒナ委員長", "zh_cn_jp": "日奈委员长", "zh_cn_tw": "阳奈委员长", "zh_cn_cn": "日奈"}, "interpage": {"prev": {"name": {"path_name": "Akari", "dev_name": "Akari", "name": {"en": "Akari", "jp": "アカリ", "zh_cn_jp": "明里", "zh_cn_tw": "亚伽里", "zh_cn_cn": "明里"}}, "namespace": ["character", "student", "akari"]}, "next": {"name": {"path_name": "Ako_Dress", "dev_name": "CH0231", "name": {"en": "Ako (Dress)", "jp": "アコ（ドレス）", "zh_cn_jp": "亚子（礼服）", "zh_cn_tw": "アコ（ドレス）", "zh_cn_cn": "亚子（礼服）"}}, "namespace": ["character", "student", "ako_dress"]}}, "combatant_info": {"squad_type": {"type": "Support", "lang": {"en": "SPECIAL", "jp": "SPECIAL", "zh_cn_jp": "后援", "zh_cn_tw": "SPECIAL", "zh_cn_cn": "支援"}}, "attack_type": {"type": "Mystic", "lang": {"en": "Mystic", "jp": "神秘", "zh_cn_jp": "神秘", "zh_cn_tw": "神秘", "zh_cn_cn": "神秘"}}, "armor_type": {"type": "HeavyArmor", "lang": {"en": "Heavy", "jp": "重装甲", "zh_cn_jp": "重型装甲", "zh_cn_tw": "重装甲", "zh_cn_cn": "重装甲"}}}, "bond_track": {"uuid": "8052c9c9-6f7a-4db3-b362-d729cc89fe6e", "no": 38, "filetype": 1, "namespace": ["track", "ost", "38"], "track_type": 0, "instance_id": "OST_38", "name": {"realname": {"en": "Guruguru Usagi", "jp": "Guruguru Usagi", "zh_cn": "Guruguru Usagi"}, "known_as": []}, "desc": {"en": "【暂无】", "jp": "【暂无】", "zh_cn": "【暂无】"}, "composer": {"composer_id": "1", "nickname": "Mitsukiyo", "contact": {"platform": {"en": "Twitter", "jp": "Twitter", "zh_cn": "Twitter"}, "url": {"platform": {"en": "Twitter", "jp": "Twitter", "zh_cn": "Twitter"}, "value": "https://twitter.com/mitsukiyo_5", "short_desc": {"en": "", "jp": "", "zh_cn": ""}}}}, "tags": [], "image": {"platform": {"en": "None", "jp": "None", "zh_cn": "None"}, "value": "/static/images/background/BG_View_Kivotos.jpg", "short_desc": {"en": "", "jp": "", "zh_cn": ""}}, "album": [], "interpage": {"prev": {"name": {"realname": {"en": "Aira", "jp": "Aira", "zh_cn": "Aira"}, "known_as": []}, "namespace": ["track", "ost", "37"], "instance_id": "OST_37", "no": 37}, "next": {"name": {"realname": {"en": "Water Drop", "jp": "Water Drop", "zh_cn": "一滴水"}, "known_as": []}, "namespace": ["track", "ost", "39"], "instance_id": "OST_39", "no": 39}}, "stats": {"is_ost": true, "is_ani": false, "is_short": false, "is_other": false, "is_ba": true, "is_jp": true, "is_global": true, "is_cn": true, "is_story": true, "is_story_main": true, "is_story_memory": true, "is_story_event": true, "is_battle": false, "is_battle_main": false, "is_battle_story": false, "is_battle_event": false, "is_segment": false, "is_sub": false, "has_related": false}}, "bond_rank": 5}}