{"uuid": "e1ec9c12-21dd-453f-b25e-d92aa49b483b", "filetype": 14, "filetype_sub": 1, "namespace": ["event", "999", "story", "44"], "name": {"en": "A Gamer's Determination", "jp": "A Gamer's Determination", "zh_cn": "永不放弃的玩家"}, "desc": [{"en": "Momoi participates in a gaming competition on Valentine's Day, but is immediately eliminated. Though her plans to give her winning trophy along with some chocolate as gifts to Sensei are ruined, Momoi gets some chocolate from a claw machine to give Sensei instead.", "jp": "Momoi participates in a gaming competition on Valentine's Day, but is immediately eliminated. Though her plans to give her winning trophy along with some chocolate as gifts to Sensei are ruined, Momoi gets some chocolate from a claw machine to give Sensei instead.", "zh_cn": "{cf桃井}信誓旦旦地参加了一场情人节游戏大赛，然而没想到她却在第一场比赛就惨遭淘汰。虽然没能按照原定计划，将优胜奖杯和巧克力一起送给老师，但{cf桃井}最后还是把自己在抽饼干游戏中获得的巧克力送给了老师。"}], "pos": {"event_id": 999, "segment": 44}, "image": {"platform": {"en": "None", "jp": "None", "zh_cn": "None"}, "value": "", "short_desc": {"en": "", "jp": "", "zh_cn": ""}}, "instance_id": "EVENT_999_44", "part": {"all": {"background": {"BG_Arcade.jpg": {"uuid": "84c92419-ac9a-4d21-bf2a-96a1d9c63c74", "filetype": 71, "filename": "BG_Arcade.jpg", "name": {"en": "BG_Arcade.jpg", "jp": "BG_Arcade.jpg", "zh_cn": "BG_Arcade.jpg"}, "desc": {"en": "neru aris arcade game store shop indoor artificial light room", "jp": "neru aris arcade game store shop indoor artificial light room", "zh_cn": "BG_Arcade.jpg Description"}, "image": {"platform": {"en": "None", "jp": "None", "zh_cn": "None"}, "value": "/static/images/background/BG_Arcade.jpg", "short_desc": {"en": "", "jp": "", "zh_cn": ""}}, "character": [], "interpage": {"prev": {"name": {"en": "BG_Amusement_Night2.jpg", "jp": "BG_Amusement_Night2.jpg", "zh_cn": "BG_Amusement_Night2.jpg"}, "namespace": ["background", "BG_Amusement_Night2.jpg"]}, "next": {"name": {"en": "BG_AriusBasilica.jpg", "jp": "BG_AriusBasilica.jpg", "zh_cn": "BG_AriusBasilica.jpg"}, "namespace": ["background", "BG_AriusBasilica.jpg"]}}}}, "character": {"Momoi": {"uuid": "Momoi", "id": 13011, "name": {"path_name": "Momoi", "dev_name": "Momoi", "family_name": {"en": "Saiba", "jp": "才羽", "zh_cn_jp": "才羽", "zh_cn_tw": "才羽", "zh_cn_cn": "才羽"}, "personal_name": {"en": "Momoi", "jp": "モモイ", "zh_cn_jp": "桃井", "zh_cn_tw": "桃井", "zh_cn_cn": "桃"}, "name": {"en": "Momoi", "jp": "モモイ", "zh_cn_jp": "桃井", "zh_cn_tw": "桃井", "zh_cn_cn": "桃"}}, "image": {"collection_bg": "BG_Millennium_Collection", "collection_texture": "13011"}, "birthday": {"localized": {"en": "December 8th", "jp": "12月8日", "zh_cn_jp": "12月8日", "zh_cn_tw": "12月8日", "zh_cn_cn": "12月8日"}, "normalized": {"en": "12/8", "jp": "12/8", "zh_cn_jp": "12/8", "zh_cn_tw": "12/8", "zh_cn_cn": "12/8"}}, "school": {"short": {"en": "Millennium", "jp": "ミレニアム", "zh_cn_jp": "千年", "zh_cn_tw": "千年", "zh_cn_cn": "千禧年"}, "long": {"en": "Millennium Science School", "jp": "ミレニアムサイエンススクール", "zh_cn_jp": "千年科学学园", "zh_cn_tw": "千年科学学园", "zh_cn_cn": "千禧年科技学院"}}, "school_id": "Millennium", "club": {"en": "Game Development Department", "jp": "ゲーム開発部", "zh_cn_jp": "游戏开发部", "zh_cn_tw": "游戏开发部", "zh_cn_cn": "游戏开发部"}, "age": {"en": "15 years old", "jp": "15歳", "zh_cn_jp": "15岁", "zh_cn_tw": "15岁", "zh_cn_cn": "15岁"}, "hobby": {"en": "Video Games", "jp": "ゲーム", "zh_cn_jp": "游戏", "zh_cn_tw": "游戏", "zh_cn_cn": "游戏"}, "interpage": {"prev": {"name": {"path_name": "Momiji", "dev_name": "Momiji", "name": {"en": "Momiji", "jp": "モミジ", "zh_cn_jp": "红叶", "zh_cn_tw": "红叶", "zh_cn_cn": "红叶"}}, "namespace": ["character", "student", "momiji"]}, "next": {"name": {"path_name": "Mutsuki", "dev_name": "Mutsuki", "name": {"en": "Mutsuki", "jp": "ムツキ", "zh_cn_jp": "睦月", "zh_cn_tw": "无月", "zh_cn_cn": "睦月"}}, "namespace": ["character", "student", "mutsuki"]}}, "combatant_info": {"squad_type": {"type": "Main", "lang": {"en": "STRIKER", "jp": "STRIKER", "zh_cn_jp": "前锋", "zh_cn_tw": "STRIKER", "zh_cn_cn": "突击"}}, "attack_type": {"type": "Pierce", "lang": {"en": "Piercing", "jp": "貫通", "zh_cn_jp": "贯通", "zh_cn_tw": "贯穿", "zh_cn_cn": "贯穿"}}, "armor_type": {"type": "LightArmor", "lang": {"en": "Light", "jp": "軽装備", "zh_cn_jp": "轻型护甲", "zh_cn_tw": "轻装甲", "zh_cn_cn": "轻装甲"}}}, "bond_track": {"uuid": "e49c0641-7d5a-4399-92f1-4cb3c21ff47c", "no": 54, "filetype": 1, "namespace": ["track", "ost", "54"], "track_type": 0, "instance_id": "OST_54", "name": {"realname": {"en": "After The Beep", "jp": "After The Beep", "zh_cn": "After The Beep"}, "known_as": []}, "desc": {"en": "【暂无】", "jp": "【暂无】", "zh_cn": "【暂无】"}, "composer": {"composer_id": "3", "nickname": "Nor", "contact": {"platform": {"en": "Twitter", "jp": "Twitter", "zh_cn": "Twitter"}, "url": {"platform": {"en": "Twitter", "jp": "Twitter", "zh_cn": "Twitter"}, "value": "https://twitter.com/NOR0910", "short_desc": {"en": "", "jp": "", "zh_cn": ""}}}}, "tags": [], "image": {"platform": {"en": "None", "jp": "None", "zh_cn": "None"}, "value": "/static/images/background/BG_View_Kivotos.jpg", "short_desc": {"en": "", "jp": "", "zh_cn": ""}}, "album": [{"uuid": "80097a34-1ab3-4064-929a-ad18a2eecc36", "filetype": 5, "album_id": "01", "name": {"en": "Blue Archive Original Soundtrack (Vol.1 ~Longing for the memorable days~)", "jp": "Blue Archive Original Soundtrack (Vol.1 ~Longing for the memorable days~)", "zh_cn": "Blue Archive Original Soundtrack (Vol.1 ~Longing for the memorable days~)"}, "desc": {"en": "Blue Archive's first original soundtrack.", "jp": "Blue Archive's first original soundtrack.", "zh_cn": "Blue Archive's first original soundtrack."}, "namespace": ["album", "01"], "cover_img": "/static/images/album/01.png", "release_date": 1648080000, "release_date_format": "2022-03-24", "disc_num": 2, "track_num": 38}], "interpage": {"prev": {"name": {"realname": {"en": "Future Lab", "jp": "Future Lab", "zh_cn": "未来实验室"}, "known_as": []}, "namespace": ["track", "ost", "53"], "instance_id": "OST_53", "no": 53}, "next": {"name": {"realname": {"en": "Moment", "jp": "Moment", "zh_cn": "那一刻"}, "known_as": []}, "namespace": ["track", "ost", "55"], "instance_id": "OST_55", "no": 55}}, "stats": {"is_ost": true, "is_ani": false, "is_short": false, "is_other": false, "is_ba": true, "is_jp": true, "is_global": true, "is_cn": true, "is_story": true, "is_story_main": false, "is_story_memory": true, "is_story_event": true, "is_battle": false, "is_battle_main": false, "is_battle_story": false, "is_battle_event": false, "is_segment": false, "is_sub": false, "has_related": false}}, "bond_rank": 6}}, "track": {"OST_64": {"uuid": "34abe431-991b-4912-95f2-70bfd14fe4e6", "no": 64, "filetype": 1, "namespace": ["track", "ost", "64"], "track_type": 0, "instance_id": "OST_64", "name": {"realname": {"en": "Pixel Time", "jp": "Pixel Time", "zh_cn": "像素时间"}, "known_as": []}, "desc": {"en": "The 64th track from Blue Archive, a widely recognized song for its appearance with the Game Development Department story. It has become the de facto identity and theme song for the GDD and its members.", "jp": "The 64th track from Blue Archive, a widely recognized song for its appearance with the Game Development Department story. It has become the de facto identity and theme song for the GDD and its members.", "zh_cn": "蔚蓝档案OST中的第64首曲子，于“游戏开发部”相关章节中广泛使用。其已经成为游戏开发部及其成员实质上的标志性曲目。"}, "composer": {"composer_id": "1", "nickname": "Mitsukiyo", "contact": {"platform": {"en": "Twitter", "jp": "Twitter", "zh_cn": "Twitter"}, "url": {"platform": {"en": "Twitter", "jp": "Twitter", "zh_cn": "Twitter"}, "value": "https://twitter.com/mitsukiyo_5", "short_desc": {"en": "", "jp": "", "zh_cn": ""}}}}, "tags": [], "image": {"platform": {"en": "None", "jp": "None", "zh_cn": "None"}, "value": "/static/images/background/BG_View_Kivotos.jpg", "short_desc": {"en": "", "jp": "", "zh_cn": ""}}, "album": [], "interpage": {"prev": {"name": {"realname": {"en": "Blooming Moon", "jp": "Blooming Moon", "zh_cn": "花好月圆"}, "known_as": []}, "namespace": ["track", "ost", "63"], "instance_id": "OST_63", "no": 63}, "next": {"name": {"realname": {"en": "Accelerator", "jp": "Accelerator", "zh_cn": "加速器"}, "known_as": []}, "namespace": ["track", "ost", "65"], "instance_id": "OST_65", "no": 65}}, "stats": {"is_ost": true, "is_ani": false, "is_short": false, "is_other": false, "is_ba": true, "is_jp": true, "is_global": true, "is_cn": true, "is_story": true, "is_story_main": true, "is_story_memory": false, "is_story_event": true, "is_battle": false, "is_battle_main": false, "is_battle_story": false, "is_battle_event": false, "is_segment": false, "is_sub": false, "has_related": true}}, "OST_15": {"uuid": "e2e928ed-f27a-4e6d-a5d3-a466ada13be2", "no": 15, "filetype": 1, "namespace": ["track", "ost", "15"], "track_type": 0, "instance_id": "OST_15", "name": {"realname": {"en": "Honey Jam", "jp": "Honey Jam", "zh_cn": "蜂蜜果酱"}, "known_as": []}, "desc": {"en": "【暂无】", "jp": "【暂无】", "zh_cn": "【暂无】"}, "composer": {"composer_id": "1", "nickname": "Mitsukiyo", "contact": {"platform": {"en": "Twitter", "jp": "Twitter", "zh_cn": "Twitter"}, "url": {"platform": {"en": "Twitter", "jp": "Twitter", "zh_cn": "Twitter"}, "value": "https://twitter.com/mitsukiyo_5", "short_desc": {"en": "", "jp": "", "zh_cn": ""}}}}, "tags": [{"uuid": "d9cce303-820e-4de6-b2ce-586bd4c76e4e", "filetype": 61, "name": {"en": "Energetic", "jp": "Energetic", "zh_cn": "超有活力"}, "desc": {"en": "<b>Example: FEEEEVER TIME, Undefined Behavior, Goal Wo Nerae!</b> Overall it coincides with the Uplifting genre and combat tracks.", "jp": "<b>Example: FEEEEVER TIME, Undefined Behavior, Goal Wo Nerae!</b> Overall it coincides with the Uplifting genre and combat tracks.", "zh_cn": "<b>举例/联想：FEEEEVER TIME、Undefined Behavior、Goal Wo Nerae!；总体上基本与Uplifting的风格和战斗曲重合。</b>"}, "namespace": ["tag", "energetic"], "color": "green", "color_css": "success", "interpage": {"prev": {"name": {"en": "Emergency", "jp": "Emergency", "zh_cn": "紧急"}, "namespace": ["tag", "emergency"]}, "next": {"name": {"en": "Failure", "jp": "Failure", "zh_cn": "失败"}, "namespace": ["tag", "failure"]}}}], "image": {"platform": {"en": "None", "jp": "None", "zh_cn": "None"}, "value": "/static/images/background/BG_View_Kivotos.jpg", "short_desc": {"en": "", "jp": "", "zh_cn": ""}}, "album": [], "interpage": {"prev": {"name": {"realname": {"en": "Step by Step", "jp": "Step by Step", "zh_cn": "一步又一步"}, "known_as": []}, "namespace": ["track", "ost", "14"], "instance_id": "OST_14", "no": 14}, "next": {"name": {"realname": {"en": "MX Adventure", "jp": "MX Adventure", "zh_cn": "未知的冒险"}, "known_as": []}, "namespace": ["track", "ost", "16"], "instance_id": "OST_16", "no": 16}}, "stats": {"is_ost": true, "is_ani": false, "is_short": false, "is_other": false, "is_ba": true, "is_jp": true, "is_global": true, "is_cn": true, "is_story": true, "is_story_main": true, "is_story_memory": false, "is_story_event": true, "is_battle": false, "is_battle_main": false, "is_battle_story": false, "is_battle_event": false, "is_segment": false, "is_sub": false, "has_related": false}}}}, "_track_to_bg": {"OST_64": ["BG_Arcade.jpg"], "OST_15": ["BG_Arcade.jpg"]}, "track_to_bg": {"OST_64": ["84c92419-ac9a-4d21-bf2a-96a1d9c63c74"], "OST_15": ["84c92419-ac9a-4d21-bf2a-96a1d9c63c74"]}, "track_to_char": {"OST_64": ["Momoi"], "OST_15": ["Momoi"]}, "bg_to_char": {"BG_Arcade.jpg": ["Momoi"]}, "bg_to_track": {"BG_Arcade.jpg": ["OST_64", "OST_15"]}, "char_to_track": {"Momoi": ["OST_64", "OST_15"]}, "_char_to_bg": {"Momoi": ["BG_Arcade.jpg"]}, "char_to_bg": {"Momoi": ["84c92419-ac9a-4d21-bf2a-96a1d9c63c74"]}, "char_to_char": {}, "special": {"flag": false, "track": null}}, "is_battle": false, "source": {"en": [], "zh_tw": [], "zh_cn_cn": [], "zh_cn_jp": []}, "interpage": {"prev": {"name": {"en": "Record It Again", "jp": "Record It Again", "zh_cn": "Record it again"}, "namespace": ["event", "999", "story", "43"], "is_battle": false, "pos": {"event_id": 999, "segment": 43}}, "next": {"name": {"en": "I Want to Be First, Sensei", "jp": "I Want to Be First, Sensei", "zh_cn": "我喜欢第一个，老师"}, "namespace": ["event", "999", "story", "45"], "is_battle": false, "pos": {"event_id": 999, "segment": 45}}}, "parent_data": [{"name": {"en": "Happy Valentine's Relationship Stories ♥", "jp": "Happy Valentine's Relationship Stories ♥", "zh_cn": "快乐♡情人节特别羁绊剧情"}, "desc": {"en": "This page displays all the related content with the event \"Happy Valentine's Relationship Stories ♥\"", "jp": "This page displays all the related content with the event \"Happy Valentine's Relationship Stories ♥\"", "zh_cn": "此页显示 快乐♡情人节特别羁绊剧情 的全部相关内容"}, "namespace": ["event", "999"], "path": "event/999", "extra_data": {}}, {"name": {"en": "Happy Valentine's Relationship Stories ♥", "jp": "Happy Valentine's Relationship Stories ♥", "zh_cn": "快乐♡情人节特别羁绊剧情"}, "desc": {"en": "This page displays all the related content with the event \"Happy Valentine's Relationship Stories ♥\"", "jp": "This page displays all the related content with the event \"Happy Valentine's Relationship Stories ♥\"", "zh_cn": "此页显示 快乐♡情人节特别羁绊剧情 的全部相关内容"}, "namespace": ["event", "999"], "path": "event/999", "extra_data": {}}]}